pipeline_taeuk4958/__init__.py
pipeline_taeuk4958/version.py
pipeline_taeuk4958/cloud/__init__.py
pipeline_taeuk4958/cloud/gs.py
pipeline_taeuk4958/configs/__init__.py
pipeline_taeuk4958/configs/config.py
pipeline_taeuk4958/configs/default_runtime.py
pipeline_taeuk4958/configs/labelme_config.py
pipeline_taeuk4958/configs/record_config.py
pipeline_taeuk4958/configs/swin_maskrcnn.py
pipeline_taeuk4958/configs/train_config.py
pipeline_taeuk4958/configs/utils.py
pipeline_taeuk4958/configs/swin_maskrcnn/__init__.py
pipeline_taeuk4958/configs/swin_maskrcnn/dataset_config.py
pipeline_taeuk4958/configs/swin_maskrcnn/mask_rcmm_r50_fpn.py
pipeline_taeuk4958/configs/swin_maskrcnn/mask_rcnn_r50_fpn.py
pipeline_taeuk4958/configs/swin_maskrcnn/schedule_1x.py
pipeline_taeuk4958/utils/__init__.py
pipeline_taeuk4958/utils/utils.py
pipeline_taeuk4958-1.3.10.dist-info/METADATA
pipeline_taeuk4958-1.3.10.dist-info/WHEEL
pipeline_taeuk4958-1.3.10.dist-info/top_level.txt
pipeline_taeuk4958-1.3.10.dist-info/RECORD
