Metadata-Version: 2.1
Name: pipeline-taeuk4958
Version: 1.3.10
Summary: package to load file from docker local in docker container during container running
Home-page: https://github.com/HibernationNo1/project_4_kubeflow_pipeline.git
Author: taeuk4958 
Author-email: taeuk4958@gmail.com
License: Apache License 2.0
Platform: UNKNOWN
Requires-Dist: numpy
Requires-Dist: addict
Requires-Dist: regex
